ksonpy/__init__.py
ksonpy/cmd_line.py
ksonpy/compiler.py
ksonpy/db.py
ksonpy/helper.py
ksonpy/kson_parser.py
ksonpy/ref.py
ksonpy-0.1.7.dist-info/LICENSE
ksonpy-0.1.7.dist-info/METADATA
ksonpy-0.1.7.dist-info/WHEEL
ksonpy-0.1.7.dist-info/entry_points.txt
ksonpy-0.1.7.dist-info/top_level.txt
ksonpy-0.1.7.dist-info/RECORD
