Metadata-Version: 2.1
Name: ksonpy
Version: 0.1.7
Summary: KSON is JSON with embedded SQL and networking
Home-page: https://gitlab.com/jacob.brazeal/ksonpy
Author: Jacob Brazeal
Author-email: jacob.brazeal@gmail.com
License: UNKNOWN
Project-URL: Bug Tracker, https://gitlab.com/jacob.brazeal/ksonpy/-/issues
Platform: UNKNOWN
Classifier: Programming Language :: Python :: 3
Classifier: License :: OSI Approved :: MIT License
Classifier: Operating System :: OS Independent
Requires-Python: >=3.8
License-File: LICENSE
Requires-Dist: requests
